{
    "name": "Integration Webhooks",
    "flow": [
        {
            "id": 1,
            "module": "gateway:CustomWebHook",
            "version": 1,
            "parameters": {
                "hook": 4028534,
                "maxResults": 1
            },
            "mapper": {},
            "metadata": {
                "designer": {
                    "x": 0,
                    "y": 0
                },
                "restore": {
                    "parameters": {
                        "hook": {
                            "data": {
                                "editable": "true"
                            },
                            "label": "My gateway-webhook webhook"
                        }
                    }
                },
                "parameters": [
                    {
                        "name": "hook",
                        "type": "hook:gateway-webhook",
                        "label": "Webhook",
                        "required": true
                    },
                    {
                        "name": "maxResults",
                        "type": "number",
                        "label": "Maximum number of results"
                    }
                ]
            }
        },
        {
            "id": 4,
            "module": "util:SetVariable2",
            "version": 1,
            "parameters": {},
            "mapper": {
                "name": "unikalnyKlucz",
                "scope": "roundtrip",
                "value": "{{md5(1.`2` + 1.`4` + 1.`5` + 1.`8` + formatDate(now; \"YYYY-MM-DD HH:mm\"))}}"
            },
            "metadata": {
                "designer": {
                    "x": 300,
                    "y": 0
                },
                "restore": {
                    "expect": {
                        "scope": {
                            "label": "One cycle"
                        }
                    }
                },
                "expect": [
                    {
                        "name": "name",
                        "type": "text",
                        "label": "Variable name",
                        "required": true
                    },
                    {
                        "name": "scope",
                        "type": "select",
                        "label": "Variable lifetime",
                        "required": true,
                        "validate": {
                            "enum": [
                                "roundtrip",
                                "execution"
                            ]
                        }
                    },
                    {
                        "name": "value",
                        "type": "any",
                        "label": "Variable value"
                    }
                ],
                "interface": [
                    {
                        "name": "unikalnyKlucz",
                        "type": "any",
                        "label": "unikalnyKlucz"
                    }
                ]
            }
        },
        {
            "id": 7,
            "module": "datastore:AddRecord",
            "version": 1,
            "parameters": {
                "datastore": 14482
            },
            "mapper": {
                "key": "{{4.unikalnyKlucz}}",
                "overwrite": false
            },
            "metadata": {
                "designer": {
                    "x": 600,
                    "y": 0
                },
                "restore": {
                    "expect": {
                        "overwrite": {
                            "mode": "chose"
                        }
                    },
                    "parameters": {
                        "datastore": {
                            "label": "My data store"
                        }
                    }
                },
                "parameters": [
                    {
                        "name": "datastore",
                        "type": "datastore",
                        "label": "Data store",
                        "required": true
                    }
                ],
                "expect": [
                    {
                        "name": "key",
                        "type": "text",
                        "label": "Key"
                    },
                    {
                        "name": "overwrite",
                        "type": "boolean",
                        "label": "Overwrite an existing record",
                        "required": true
                    }
                ]
            },
            "onerror": [
                {
                    "id": 10,
                    "module": "builtin:Resume",
                    "version": 1,
                    "metadata": {
                        "designer": {
                            "x": 889,
                            "y": 252
                        }
                    }
                }
            ]
        },
        {
            "id": 11,
            "module": "airtable:ActionCreateRecord",
            "version": 3,
            "parameters": {
                "__IMTCONN__": 13876048
            },
            "mapper": {
                "base": "apphteWatdniiWHuh",
                "table": "tbliiX4CiJF1mMTdQ",
                "record": {
                    "fld0DSzpPZXLmftJu": "{{1.`4`}}",
                    "fldB6gTQ9vm97ue9z": "{{1.`4`}}",
                    "fldSjOnSQwYPSGqtC": "{{1.`2`}}",
                    "fldSkAgwvtjekJthz": true,
                    "fldZmEfqLrw9d06fQ": "{{1.`5`}}",
                    "fldjNp4Tmp9TzHEuz": "{{1.email}}",
                    "fldpo6lnPScLJ5V6p": "{{1.`8`}}",
                    "fldunHsDIAtl8gwdj": "zw, Nieprzekroczony limit obrotu 200 000 zł w poprzednim roku podatkowym uprawnia do zwolnienia z VAT (zgodnie z art. 113 ust. 1 i 9 ustawy o VAT).",
                    "fldxlkaIxH0kkZEz2": "100",
                    "fldyXKAuP5ni2Q3e6": "Strona WWW, zaliczka "
                },
                "typecast": false,
                "useColumnId": false
            },
            "metadata": {
                "designer": {
                    "x": 925,
                    "y": -165
                },
                "restore": {
                    "expect": {
                        "base": {
                            "label": "autofaktura"
                        },
                        "table": {
                            "label": "Imię itd.",
                            "nested": [
                                {
                                    "name": "record",
                                    "spec": [
                                        {
                                            "name": "fldpo6lnPScLJ5V6p",
                                            "type": "text",
                                            "label": "Twój Klient"
                                        },
                                        {
                                            "name": "fldSjOnSQwYPSGqtC",
                                            "type": "text",
                                            "label": "NIP klienta"
                                        },
                                        {
                                            "name": "fld0DSzpPZXLmftJu",
                                            "type": "text",
                                            "label": "Miejscowość"
                                        },
                                        {
                                            "name": "fldZmEfqLrw9d06fQ",
                                            "type": "text",
                                            "label": "Kod pocztowy:"
                                        },
                                        {
                                            "name": "fldB6gTQ9vm97ue9z",
                                            "type": "text",
                                            "label": "Ulica i numer"
                                        },
                                        {
                                            "name": "fldyXKAuP5ni2Q3e6",
                                            "type": "text",
                                            "label": "Oferta"
                                        },
                                        {
                                            "name": "fldxlkaIxH0kkZEz2",
                                            "type": "text",
                                            "label": "Cena w PLN"
                                        },
                                        {
                                            "mode": "edit",
                                            "name": "fldunHsDIAtl8gwdj",
                                            "type": "select",
                                            "label": "VAT",
                                            "dynamic": true,
                                            "options": [
                                                {
                                                    "label": "23",
                                                    "value": "23"
                                                },
                                                {
                                                    "label": "22",
                                                    "value": "22"
                                                },
                                                {
                                                    "label": "8",
                                                    "value": "8"
                                                },
                                                {
                                                    "label": "7",
                                                    "value": "7"
                                                },
                                                {
                                                    "label": "5",
                                                    "value": "5"
                                                },
                                                {
                                                    "label": "0",
                                                    "value": "0"
                                                },
                                                {
                                                    "label": "zw, Nieprzekroczony limit obrotu 200 000 zł w poprzednim roku podatkowym uprawnia do zwolnienia z VAT (zgodnie z art. 113 ust. 1 i 9 ustawy o VAT).",
                                                    "value": "zw, Nieprzekroczony limit obrotu 200 000 zł w poprzednim roku podatkowym uprawnia do zwolnienia z VAT (zgodnie z art. 113 ust. 1 i 9 ustawy o VAT)."
                                                },
                                                {
                                                    "label": "zw, Zwolnienie ze względu na rodzaj prowadzonej działalności (art. 43 ust 1 ustawy o VAT)",
                                                    "value": "zw, Zwolnienie ze względu na rodzaj prowadzonej działalności (art. 43 ust 1 ustawy o VAT)"
                                                },
                                                {
                                                    "label": "zw, Zwolnienie na mocy rozporządzenia MF (art. 82 ust 3 ustawy o VAT)",
                                                    "value": "zw, Zwolnienie na mocy rozporządzenia MF (art. 82 ust 3 ustawy o VAT)"
                                                },
                                                {
                                                    "label": "np",
                                                    "value": "np"
                                                }
                                            ],
                                            "validate": false
                                        },
                                        {
                                            "name": "fldKt8YSaIrv7VSD6",
                                            "type": "text",
                                            "label": "Twoja faktura",
                                            "multiline": true
                                        },
                                        {
                                            "name": "fldjNp4Tmp9TzHEuz",
                                            "type": "text",
                                            "label": "Email"
                                        },
                                        {
                                            "name": "fldSkAgwvtjekJthz",
                                            "type": "boolean",
                                            "label": "newslater"
                                        }
                                    ],
                                    "type": "collection",
                                    "label": "Record"
                                }
                            ]
                        },
                        "record": {
                            "nested": {
                                "fldSkAgwvtjekJthz": {
                                    "mode": "chose"
                                },
                                "fldunHsDIAtl8gwdj": {
                                    "mode": "chose",
                                    "label": "zw, Nieprzekroczony limit obrotu 200 000 zł w poprzednim roku podatkowym uprawnia do zwolnienia z VAT (zgodnie z art. 113 ust. 1 i 9 ustawy o VAT)."
                                }
                            }
                        },
                        "typecast": {
                            "mode": "chose"
                        },
                        "useColumnId": {
                            "mode": "chose"
                        }
                    },
                    "parameters": {
                        "__IMTCONN__": {
                            "data": {
                                "scoped": "true",
                                "connection": "airtable3"
                            },
                            "label": "impozit-konto(auto-zbieracz-itd.) (User ID: usr0zvL9B1EbfTegV)"
                        }
                    }
                },
                "parameters": [
                    {
                        "name": "__IMTCONN__",
                        "type": "account:airtable3,airtable2",
                        "label": "Connection",
                        "required": true
                    }
                ],
                "expect": [
                    {
                        "name": "base",
                        "type": "select",
                        "label": "Base",
                        "required": true
                    },
                    {
                        "name": "typecast",
                        "type": "boolean",
                        "label": "Smart links",
                        "required": true
                    },
                    {
                        "name": "useColumnId",
                        "type": "boolean",
                        "label": "Use Column ID",
                        "required": true
                    },
                    {
                        "name": "table",
                        "type": "select",
                        "label": "Table",
                        "required": true
                    },
                    {
                        "name": "record",
                        "spec": [
                            {
                                "name": "fldpo6lnPScLJ5V6p",
                                "type": "text",
                                "label": "Twój Klient"
                            },
                            {
                                "name": "fldSjOnSQwYPSGqtC",
                                "type": "text",
                                "label": "NIP klienta"
                            },
                            {
                                "name": "fld0DSzpPZXLmftJu",
                                "type": "text",
                                "label": "Miejscowość"
                            },
                            {
                                "name": "fldZmEfqLrw9d06fQ",
                                "type": "text",
                                "label": "Kod pocztowy:"
                            },
                            {
                                "name": "fldB6gTQ9vm97ue9z",
                                "type": "text",
                                "label": "Ulica i numer"
                            },
                            {
                                "name": "fldyXKAuP5ni2Q3e6",
                                "type": "text",
                                "label": "Oferta"
                            },
                            {
                                "name": "fldxlkaIxH0kkZEz2",
                                "type": "text",
                                "label": "Cena w PLN"
                            },
                            {
                                "mode": "edit",
                                "name": "fldunHsDIAtl8gwdj",
                                "type": "select",
                                "label": "VAT"
                            },
                            {
                                "name": "fldKt8YSaIrv7VSD6",
                                "type": "text",
                                "label": "Twoja faktura"
                            },
                            {
                                "name": "fldjNp4Tmp9TzHEuz",
                                "type": "text",
                                "label": "Email"
                            },
                            {
                                "name": "fldSkAgwvtjekJthz",
                                "type": "boolean",
                                "label": "newslater"
                            }
                        ],
                        "type": "collection",
                        "label": "Record"
                    }
                ],
                "interface": [
                    {
                        "name": "id",
                        "type": "text",
                        "label": "ID"
                    },
                    {
                        "name": "createdTime",
                        "type": "date",
                        "label": "Created Time"
                    },
                    {
                        "name": "Twój Klient",
                        "type": "text",
                        "label": "Twój Klient"
                    },
                    {
                        "name": "NIP klienta",
                        "type": "text",
                        "label": "NIP klienta"
                    },
                    {
                        "name": "Miejscowość",
                        "type": "text",
                        "label": "Miejscowość"
                    },
                    {
                        "name": "Kod pocztowy:",
                        "type": "text",
                        "label": "Kod pocztowy:"
                    },
                    {
                        "name": "Ulica i numer",
                        "type": "text",
                        "label": "Ulica i numer"
                    },
                    {
                        "name": "Oferta",
                        "type": "text",
                        "label": "Oferta"
                    },
                    {
                        "name": "Cena w PLN",
                        "type": "text",
                        "label": "Cena w PLN"
                    },
                    {
                        "name": "VAT",
                        "type": "text",
                        "label": "VAT"
                    },
                    {
                        "name": "Twoja faktura",
                        "type": "text",
                        "label": "Twoja faktura",
                        "multiline": true
                    },
                    {
                        "name": "Data utworzenia ⏰",
                        "type": "date",
                        "label": "Data utworzenia ⏰"
                    },
                    {
                        "name": "Email",
                        "type": "text",
                        "label": "Email"
                    },
                    {
                        "name": "newslater",
                        "type": "boolean",
                        "label": "newslater"
                    }
                ]
            }
        },
        {
            "id": 12,
            "module": "datastore:DeleteRecord",
            "version": 1,
            "parameters": {
                "datastore": 14482
            },
            "mapper": {
                "key": "{{7.key}}"
            },
            "metadata": {
                "designer": {
                    "x": 1225,
                    "y": -165
                },
                "restore": {
                    "parameters": {
                        "datastore": {
                            "label": "My data store"
                        }
                    }
                },
                "parameters": [
                    {
                        "name": "datastore",
                        "type": "datastore",
                        "label": "Data store",
                        "required": true
                    }
                ],
                "expect": [
                    {
                        "name": "key",
                        "type": "text",
                        "label": "Key",
                        "required": true
                    }
                ]
            }
        },
        {
            "id": 13,
            "module": "http:MakeRequest",
            "version": 4,
            "parameters": {
                "tlsType": "",
                "proxyKeychain": "",
                "authenticationType": "noAuth"
            },
            "mapper": {
                "url": "https://pomaski-szymek.fakturownia.pl/invoices.json",
                "method": "post",
                "headers": [
                    {
                        "name": "Accept",
                        "value": "application/json"
                    },
                    {
                        "name": "Content-Type",
                        "value": "application/json"
                    }
                ],
                "contentType": "json",
                "inputMethod": "jsonString",
                "shareCookies": false,
                "parseResponse": true,
                "allowRedirects": true,
                "stopOnHttpError": true,
                "jsonStringBodyContent": "{\n  \"api_token\": \"GkrFRl4sVyhMoCcZDPgg\",\n  \"invoice\": {\n    \"description\": \"{{switch(23; 23; \"Brak\"; 22; \"Brak\"; 8; \"Brak\"; 7; \"Brak\"; 5; \"Brak\"; 0; \"Brak\"; 23)}}\",\n    \"income\": \"1\",\n    \"kind\": \"vat\",\n    \"number\": \"\",\n    \"sell_date\": \"\",\n    \"issue_date\": \"\",\n    \"payment_to\": \"\",\n\"buyer_email\": \"{{11.Email}}\",\n    \"buyer_tax_no\": \"{{11.`NIP klienta`}}\",\n    \"buyer_city\": \"{{11.`Miejscowość`}}\",\n     \"buyer_street\": \"{{11.`Ulica i numer`}}\",\n     \"buyer_post_code\": \"{{11.`Kod pocztowy:`}}\",       \n     \"buyer_name\": \"{{11.`Twój Klient`}}\",\n    \"seller_name\": \"\",\n    \"positions\": [\n      {\n        \"name\": \"{{11.Oferta}}\",\n        \"tax\": \"{{switch(23; \"zw, Nieprzekroczony limit obrotu 200 000 zł w poprzednim roku podatkowym uprawnia do zwolnienia z VAT (zgodnie z art. 113 ust. 1 i 9 ustawy o VAT).\"; \"zw\"; \"zw, Zwolnienie ze względu na rodzaj prowadzonej działalności (art. 43 ust 1 ustawy o VAT)\"; \"zw\"; \"zw, Zwolnienie na mocy rozporządzenia MF (art. 82 ust 3 ustawy o VAT)\"; \"zw\"; 23)}}\", \n        \"total_price_gross\": \"{{11.`Cena w PLN`}}\",\n        \"quantity\": \"1\",\n        \"quantity_unit\": \"dni.\" \n      }\n    ]\n  }\n}",
                "requestCompressedContent": true
            },
            "metadata": {
                "designer": {
                    "x": 1602,
                    "y": -159
                },
                "restore": {
                    "expect": {
                        "method": {
                            "mode": "chose",
                            "label": "POST"
                        },
                        "headers": {
                            "mode": "chose",
                            "items": [
                                null,
                                null
                            ]
                        },
                        "contentType": {
                            "label": "application/jsonEnter data in the JSON format, as a string or using a data structure."
                        },
                        "inputMethod": {
                            "label": "JSON stringEnter the JSON body as a raw text string. If values contain JSON reserved characters, you must escape them manually."
                        },
                        "shareCookies": {
                            "mode": "chose"
                        },
                        "parseResponse": {
                            "mode": "chose"
                        },
                        "allowRedirects": {
                            "mode": "chose"
                        },
                        "paginationType": {
                            "label": "Empty"
                        },
                        "queryParameters": {
                            "mode": "chose"
                        },
                        "stopOnHttpError": {
                            "mode": "chose"
                        },
                        "requestCompressedContent": {
                            "mode": "chose"
                        }
                    },
                    "parameters": {
                        "tlsType": {
                            "label": "Empty"
                        },
                        "proxyKeychain": {
                            "label": "Choose a key"
                        },
                        "authenticationType": {
                            "label": "No authenticationUse when no credentials are required for the request."
                        }
                    }
                },
                "parameters": [
                    {
                        "name": "authenticationType",
                        "type": "select",
                        "label": "Authentication type",
                        "required": true,
                        "validate": {
                            "enum": [
                                "noAuth",
                                "apiKey",
                                "basicAuth",
                                "oAuth"
                            ]
                        }
                    },
                    {
                        "name": "tlsType",
                        "type": "select",
                        "label": "Transport layer security (TLS)",
                        "validate": {
                            "enum": [
                                "mTls",
                                "tls"
                            ]
                        }
                    },
                    {
                        "name": "proxyKeychain",
                        "type": "keychain:proxy",
                        "label": "Proxy"
                    }
                ],
                "expect": [
                    {
                        "name": "url",
                        "type": "url",
                        "label": "URL",
                        "required": true
                    },
                    {
                        "name": "method",
                        "type": "select",
                        "label": "Method",
                        "required": true,
                        "validate": {
                            "enum": [
                                "get",
                                "head",
                                "post",
                                "put",
                                "patch",
                                "delete",
                                "options"
                            ]
                        }
                    },
                    {
                        "name": "headers",
                        "spec": {
                            "name": "value",
                            "spec": [
                                {
                                    "name": "name",
                                    "type": "text",
                                    "label": "Name",
                                    "required": true,
                                    "validate": {
                                        "pattern": "^[-!#$%&'*+.^_`|~0-9A-Za-z]+$"
                                    }
                                },
                                {
                                    "name": "value",
                                    "type": "text",
                                    "label": "Value"
                                }
                            ],
                            "type": "collection",
                            "label": "Header"
                        },
                        "type": "array",
                        "label": "Headers"
                    },
                    {
                        "name": "queryParameters",
                        "spec": {
                            "name": "value",
                            "spec": [
                                {
                                    "name": "name",
                                    "type": "text",
                                    "label": "Name",
                                    "required": true
                                },
                                {
                                    "name": "value",
                                    "type": "text",
                                    "label": "Value"
                                }
                            ],
                            "type": "collection",
                            "label": "Parameter"
                        },
                        "type": "array",
                        "label": "Query parameters"
                    },
                    {
                        "name": "contentType",
                        "type": "select",
                        "label": "Body content type",
                        "validate": {
                            "enum": [
                                "json",
                                "multipart",
                                "urlEncoded",
                                "custom"
                            ]
                        }
                    },
                    {
                        "name": "parseResponse",
                        "type": "boolean",
                        "label": "Parse response",
                        "required": true
                    },
                    {
                        "name": "stopOnHttpError",
                        "type": "boolean",
                        "label": "Return error if HTTP request fails",
                        "required": true
                    },
                    {
                        "name": "timeout",
                        "type": "uinteger",
                        "label": "Timeout",
                        "validate": {
                            "max": 300,
                            "min": 1
                        }
                    },
                    {
                        "name": "allowRedirects",
                        "type": "boolean",
                        "label": "Allow redirects",
                        "required": true
                    },
                    {
                        "name": "shareCookies",
                        "type": "boolean",
                        "label": "Share cookies with other HTTP modules",
                        "required": true
                    },
                    {
                        "name": "requestCompressedContent",
                        "type": "boolean",
                        "label": "Request compressed content",
                        "required": true
                    },
                    {
                        "name": "inputMethod",
                        "type": "select",
                        "label": "Body input method",
                        "required": true,
                        "validate": {
                            "enum": [
                                "dataStructure",
                                "jsonString"
                            ]
                        }
                    },
                    {
                        "name": "jsonStringBodyContent",
                        "type": "text",
                        "label": "Body content",
                        "required": true
                    },
                    {
                        "name": "paginationType",
                        "type": "select",
                        "label": "Pagination type",
                        "validate": {
                            "enum": [
                                "offsetBased",
                                "pageBased",
                                "urlBased",
                                "tokenBased"
                            ]
                        }
                    }
                ],
                "interface": [
                    {
                        "name": "data",
                        "type": "any",
                        "label": "Data"
                    },
                    {
                        "name": "statusCode",
                        "type": "number",
                        "label": "Status Code"
                    },
                    {
                        "name": "headers",
                        "spec": [
                            {
                                "name": "content-length",
                                "type": "text",
                                "label": "Content-Length"
                            },
                            {
                                "name": "content-encoding",
                                "type": "text",
                                "label": "Content-Encoding"
                            },
                            {
                                "name": "content-type",
                                "type": "text",
                                "label": "Content-Type"
                            },
                            {
                                "name": "server",
                                "type": "text",
                                "label": "Server"
                            },
                            {
                                "name": "cache-control",
                                "type": "text",
                                "label": "Cache-Control"
                            },
                            {
                                "name": "set-cookie",
                                "spec": {
                                    "type": "text"
                                },
                                "type": "array",
                                "label": "Set-Cookie"
                            }
                        ],
                        "type": "collection",
                        "label": "Headers"
                    }
                ]
            }
        }
    ],
    "metadata": {
        "instant": true,
        "version": 1,
        "scenario": {
            "roundtrips": 1,
            "maxErrors": 3,
            "autoCommit": true,
            "autoCommitTriggerLast": true,
            "sequential": false,
            "slots": null,
            "confidential": false,
            "dataloss": false,
            "dlq": false,
            "freshVariables": false
        },
        "designer": {
            "orphans": []
        },
        "zone": "eu2.make.com",
        "notes": []
    }
}
